{"cameraMode":{"drawMode":0,"name":"Shaded","section":"Shading Mode"},"sceneLighting":false,"audioPlay":false,"sceneViewState":{"m_AlwaysRefresh":false,"showFog":true,"showSkybox":false,"showFlares":true,"showImageEffects":true,"showParticleSystems":true,"showVisualEffectGraphs":true,"m_FxEnabled":true},"in2DMode":false,"pivot":{"x":1.5312297344207764,"y":1.8115949630737305,"z":-12.731368064880371},"rotation":{"x":-0.13863243162631989,"y":-0.7849964499473572,"z":0.18993432819843293,"w":-0.573233425617218},"size":0.16462285816669465,"orthographic":false}